{
  "endpoint_id": "5a4b9e21-441f-4bc7-9d5e-41917b4357e6",
  "connector": "wise",
  "name": "Transfers",
  "endpoint": "/v1/transfers",
  "method": "GET",
  "replication_filter_mapping": {
    "created": "createdDateStart"
  },
  "pagination": {
    "type": "offset",
    "params": {
      "limit_param": "limit",
      "offset_param": "offset"
    }
  },
  "response_schema": {
    "$schema": "https://json-schema.org/draft/2020-12/schema",
    "title": "Transfers List",
    "type": "array",
    "items": {
      "type": "object",
      "properties": {
        "id": {"type": "integer"},
        "status": {"type": "string"},
        "created": {"type": "string", "format": "date-time"},
        "sourceValue": {"type": "number"},
        "targetValue": {"type": "number"},
        "sourceCurrency": {"type": "string"},
        "targetCurrency": {"type": "string"},
        "rate": {"type": "number"}
      }
    }
  }
}
